{
    "start": {
        "U": [
            [
                "G",
                "R",
                "B"
            ],
            [
                "G",
                "W",
                "B"
            ],
            [
                "O",
                "O",
                "Y"
            ]
        ],
        "L": [
            [
                "Y",
                "W",
                "G"
            ],
            [
                "R",
                "O",
                "Y"
            ],
            [
                "R",
                "B",
                "R"
            ]
        ],
        "F": [
            [
                "W",
                "W",
                "O"
            ],
            [
                "O",
                "G",
                "G"
            ],
            [
                "B",
                "Y",
                "Y"
            ]
        ],
        "R": [
            [
                "B",
                "O",
                "O"
            ],
            [
                "O",
                "R",
                "R"
            ],
            [
                "G",
                "Y",
                "G"
            ]
        ],
        "B": [
            [
                "W",
                "W",
                "O"
            ],
            [
                "B",
                "B",
                "G"
            ],
            [
                "W",
                "B",
                "B"
            ]
        ],
        "D": [
            [
                "Y",
                "G",
                "R"
            ],
            [
                "Y",
                "Y",
                "R"
            ],
            [
                "W",
                "W",
                "R"
            ]
        ]
    },
    "end": {
        "w": [
            [
                "w6",
                "w7",
                "w8"
            ],
            [
                "w3",
                "w4",
                "w5"
            ],
            [
                "w0",
                "w1",
                "w2"
            ]
        ],
        "r": [
            [
                "r6",
                "r7",
                "r8"
            ],
            [
                "r3",
                "r4",
                "r5"
            ],
            [
                "r0",
                "r1",
                "r2"
            ]
        ],
        "g": [
            [
                "g6",
                "g7",
                "g8"
            ],
            [
                "g3",
                "g4",
                "g5"
            ],
            [
                "g0",
                "g1",
                "g2"
            ]
        ],
        "o": [
            [
                "o6",
                "o7",
                "o8"
            ],
            [
                "o3",
                "o4",
                "o5"
            ],
            [
                "o0",
                "o1",
                "o2"
            ]
        ],
        "y": [
            [
                "y6",
                "y7",
                "y8"
            ],
            [
                "y3",
                "y4",
                "y5"
            ],
            [
                "y0",
                "y1",
                "y2"
            ]
        ],
        "b": [
            [
                "b6",
                "b7",
                "b8"
            ],
            [
                "b3",
                "b4",
                "b5"
            ],
            [
                "b0",
                "b1",
                "b2"
            ]
        ]
    }
}